Metadata-Version: 2.1
Name: hbp-neuromorphic-platform
Version: 0.11.2
Summary: Client software for the EBRAINS Neuromorphic Computing Platform
Home-page: https://github.com/HumanBrainProject/hbp-neuromorphic-client
Author: Andrew P. Davison and Domenico Guarino
Author-email: andrew.davison@cnrs.fr
License: License :: OSI Approved :: Apache Software License
Platform: UNKNOWN
Classifier: Development Status :: 4 - Beta
Classifier: Intended Audience :: Science/Research
Classifier: License :: Other/Proprietary License
Classifier: Natural Language :: English
Classifier: Operating System :: OS Independent
Classifier: Programming Language :: Python :: 3
Classifier: Programming Language :: Python :: 3.8
Classifier: Programming Language :: Python :: 3.9
Classifier: Programming Language :: Python :: 3.10
Classifier: Topic :: Scientific/Engineering
License-File: LICENCE.txt
